wtg_seal/__init__.py
wtgseal/__init__.py
wtgseal/cli.py
wtgseal/maker.py
wtgseal/utils.py
wtg_seal-0.4.0.dist-info/AUTHORS.rst
wtg_seal-0.4.0.dist-info/LICENSE.txt
wtg_seal-0.4.0.dist-info/METADATA
wtg_seal-0.4.0.dist-info/WHEEL
wtg_seal-0.4.0.dist-info/entry_points.txt
wtg_seal-0.4.0.dist-info/top_level.txt
wtg_seal-0.4.0.dist-info/RECORD
