Metadata-Version: 2.1
Name: wtg-seal
Version: 0.4.0
Summary: A web traffic generator based on SURGE, Statistics and Locust
Home-page: https://github.com/mchoji/wtg-seal
Author: M. Choji
Author-email: mchoji@users.noreply.github.com
License: gpl3
Project-URL: Documentation, https://wtg-seal.readthedocs.io
Platform: any
Classifier: Development Status :: 5 - Production/Stable
Classifier: Environment :: Console
Classifier: Intended Audience :: Developers
Classifier: License :: OSI Approved :: GNU General Public License v3 or later (GPLv3+)
Classifier: Operating System :: OS Independent
Classifier: Programming Language :: Python
Classifier: Programming Language :: Python :: 3.8
Classifier: Topic :: Software Development :: Testing :: Traffic Generation
Requires-Python: >=3.8
Requires-Dist: locust (<=2.0,>=1.0)
Requires-Dist: scipy (<=2.0,>=1.4)
Provides-Extra: testing
Requires-Dist: pytest ; extra == 'testing'
Requires-Dist: pytest-cov ; extra == 'testing'
